LICENSE
flare_explorer/__init__.py
flare_explorer/address.py
flare_explorer/block.py
flare_explorer/exceptions.py
flare_explorer/gql_client.py
flare_explorer/token_transfers.py
flare_explorer/transaction.py
flare_explorer_python-1.0.0.dist-info/LICENSE
flare_explorer_python-1.0.0.dist-info/METADATA
flare_explorer_python-1.0.0.dist-info/WHEEL
flare_explorer_python-1.0.0.dist-info/RECORD
