Metadata-Version: 2.1
Name: flare-explorer-python
Version: 1.0.0
Summary: A lightweight library that works as a connector to the Flare explorer api
Home-page: https://github.com/james-ecd/flare-explorer-python
License: MIT
Keywords: flare-explorer,flare,network,api,crypto,blockchain
Author: James Davis
Author-email: jamesecd@gmail.com
Requires-Python: >=3.10,<4.0
Classifier: Development Status :: 5 - Production/Stable
Classifier: License :: OSI Approved :: MIT License
Classifier: Operating System :: OS Independent
Classifier: Programming Language :: Python :: 3
Classifier: Programming Language :: Python :: 3.10
Classifier: Programming Language :: Python :: 3.11
Classifier: Programming Language :: Python :: 3.12
Classifier: Topic :: Software Development :: Libraries :: Python Modules
Requires-Dist: gql (>=3.5.0,<4.0.0)
Requires-Dist: pydantic (>=2.11.0,<3.0.0)
Requires-Dist: requests (>=2.32.0,<3.0.0)
Requires-Dist: requests-toolbelt (>=1.0.0,<2.0.0)
Project-URL: Repository, https://github.com/james-ecd/flare-explorer-python
